{
  "schema": "dashboard-meta.v1",
  "version": "29a47f346af2bbab",
  "generated_at": "2026-06-29T16:30:53Z",
  "summary_path": "data/dashboard-summary.json",
  "source_pr_count": 269861,
  "row_count": 25036,
  "source_files": [
    {
      "path": "data/ethereum_merged_prs.csv",
      "org": "ethereum",
      "raw_pr_count": 58589,
      "summary_row_count": 8228,
      "last_updated": "2026-06-29T16:16:52Z"
    },
    {
      "path": "data/bitcoin_merged_prs.csv",
      "org": "bitcoin",
      "raw_pr_count": 17931,
      "summary_row_count": 1481,
      "last_updated": "2026-06-29T16:16:56Z"
    },
    {
      "path": "data/aave_merged_prs.csv",
      "org": "aave",
      "raw_pr_count": 5202,
      "summary_row_count": 482,
      "last_updated": "2026-06-29T16:17:50Z"
    },
    {
      "path": "data/uniswap_merged_prs.csv",
      "org": "uniswap",
      "raw_pr_count": 15066,
      "summary_row_count": 1548,
      "last_updated": "2026-06-29T16:19:38Z"
    },
    {
      "path": "data/ripple_merged_prs.csv",
      "org": "ripple",
      "raw_pr_count": 4831,
      "summary_row_count": 403,
      "last_updated": "2026-06-29T16:20:30Z"
    },
    {
      "path": "data/bnb_merged_prs.csv",
      "org": "bnb",
      "raw_pr_count": 11086,
      "summary_row_count": 1301,
      "last_updated": null
    },
    {
      "path": "data/doge_merged_prs.csv",
      "org": "doge",
      "raw_pr_count": 1601,
      "summary_row_count": 257,
      "last_updated": null
    },
    {
      "path": "data/hype_merged_prs.csv",
      "org": "hype",
      "raw_pr_count": 244,
      "summary_row_count": 120,
      "last_updated": null
    },
    {
      "path": "data/tron_merged_prs.csv",
      "org": "tron",
      "raw_pr_count": 7263,
      "summary_row_count": 658,
      "last_updated": null
    },
    {
      "path": "data/cardano_merged_prs.csv",
      "org": "cardano",
      "raw_pr_count": 33821,
      "summary_row_count": 3331,
      "last_updated": null
    },
    {
      "path": "data/stellar_merged_prs.csv",
      "org": "stellar",
      "raw_pr_count": 27621,
      "summary_row_count": 1884,
      "last_updated": "2026-06-29T16:26:33Z"
    },
    {
      "path": "data/link_merged_prs.csv",
      "org": "link",
      "raw_pr_count": 44786,
      "summary_row_count": 2682,
      "last_updated": null
    },
    {
      "path": "data/solana_merged_prs.csv",
      "org": "solana",
      "raw_pr_count": 41820,
      "summary_row_count": 2661,
      "last_updated": null
    }
  ]
}
